README.rst
setup.py
covid_ru/__init__.py
covid_ru.egg-info/PKG-INFO
covid_ru.egg-info/SOURCES.txt
covid_ru.egg-info/dependency_links.txt
covid_ru.egg-info/entry_points.txt
covid_ru.egg-info/requires.txt
covid_ru.egg-info/top_level.txt