Metadata-Version: 1.1
Name: covid-ru
Version: 0.0.8
Summary: Getting latest covid-19 stats in Russia to your cli
Home-page: https://github.com/strizhechenko/covid-ru
Author: Oleg Strizhechenko
Author-email: oleg.strizhechenko@gmail.com
License: MIT
Platform: UNKNOWN
Classifier: Development Status :: 4 - Beta
Classifier: License :: Public Domain
Classifier: Environment :: Console
Classifier: Operating System :: OS Independent
Classifier: Topic :: Internet :: WWW/HTTP :: Dynamic Content :: News/Diary
Classifier: Programming Language :: Python :: 3.7
